radman/__init__.py
radman-0.0.5.dist-info/LICENSE
radman-0.0.5.dist-info/METADATA
radman-0.0.5.dist-info/WHEEL
radman-0.0.5.dist-info/top_level.txt
radman-0.0.5.dist-info/RECORD
