Metadata-Version: 2.1
Name: radman
Version: 0.0.5
Summary: Python Package for interfacing with Radman APIs
Author-email: Daniel Carrion <daniel.carrion@monashhealth.org>
Project-URL: Homepage, https://github.com/mhmedphys/radman-python
Project-URL: Issues, https://github.com/mhmedphys/radman-python/issues
Classifier: Programming Language :: Python :: 3
Classifier: License :: OSI Approved :: MIT License
Classifier: Operating System :: OS Independent
Requires-Python: >=3.8
License-File: LICENSE
Requires-Dist: requests >=2
